checkip/__init__.py
checkip/cli.py
checkip/exceptions.py
checkip/providers.py
checkip-1.2.0.dist-info/LICENSE.md
checkip-1.2.0.dist-info/METADATA
checkip-1.2.0.dist-info/WHEEL
checkip-1.2.0.dist-info/entry_points.txt
checkip-1.2.0.dist-info/top_level.txt
checkip-1.2.0.dist-info/RECORD
