Metadata-Version: 2.1
Name: checkip
Version: 1.2.0
Summary: Resolves public (WAN) IP from supported providers.
Home-page: https://github.com/tsredanovic/checkip
Author: Toni Sredanovic
Author-email: toni.sredanovic@gmail.com
License: UNKNOWN
Project-URL: Bug Tracker, https://github.com/tsredanovic/checkip/issues
Platform: UNKNOWN
Classifier: Programming Language :: Python :: 3
Classifier: License :: OSI Approved :: MIT License
Classifier: Operating System :: OS Independent
Requires-Python: >=3.6
License-File: LICENSE.md
Requires-Dist: requests
